{
    "name": "MicroX",
    "description": "An all-in-one (beta) extension for micro:bit supporting multiple hardware modules, e.g. boards, sensors, motors, servos.",
    "icon": "./docs/static/libs/icon.png",
    "dependencies": {
        "core": "*",
        "ws2812b": "github:Microsoft/pxt-ws2812b#v0.1.1",
        "microphone": "*"
    },
    "files": [
        "ux.ts",
        "uxRemotes.ts",
        "uxMotion.ts",
        "uxSensors.ts",
        "uxDisplays.ts",
        "uxMp3.ts",
        "README.md"
    ],
    "testFiles": [
        "exampleYahboomRemote.ts",
        "exampleRobotbit.ts",
        "exampleSuperbit.ts",
        "examplePowerbrick.ts"
    ],
    "public": true
}
